{
  "recentFiles": [
    {
      "basename": "1 - Identity & Appearance",
      "path": "Writing/Antitheriomorphosis/Characters/Godzilla/1 - Identity & Appearance.md"
    },
    {
      "basename": "The Psionic and Sorcery Divisions",
      "path": "Writing/Antitheriomorphosis/Characters/The Psionic and Sorcery Divisions.md"
    },
    {
      "basename": "Godzilla, the King of the Monsters II",
      "path": "Writing/Antitheriomorphosis/Unrefined/Godzilla, the King of the Monsters II.md"
    },
    {
      "basename": "Godzilla, the King of the Monsters",
      "path": "Writing/Antitheriomorphosis/Characters/Godzilla II/Godzilla, the King of the Monsters.md"
    },
    {
      "basename": "Barb, the Turncoat Parasite",
      "path": "Writing/Antitheriomorphosis/Characters/Barb, the Turncoat Parasite.md"
    },
    {
      "basename": "Titanus Gojira",
      "path": "Writing/Antitheriomorphosis/Unrefined/Titanus Gojira.md"
    },
    {
      "basename": "Domination of Energy",
      "path": "Writing/Antitheriomorphosis/Canvases/Domination of Energy.canvas"
    },
    {
      "basename": "Physical Appearance ",
      "path": "Writing/Antitheriomorphosis/Characters/Godzilla - Refined/Identity/Physical Appearance .md"
    },
    {
      "basename": "Antitheriomorphosis",
      "path": "Writing/Antitheriomorphosis/Antitheriomorphosis.md"
    },
    {
      "basename": "Wardens - Human Identities",
      "path": "Writing/Antitheriomorphosis/Wardens - Human Identities.md"
    },
    {
      "basename": "Mothra, the Queen of the Monsters",
      "path": "Writing/Antitheriomorphosis/Characters/Mothra, the Queen of the Monsters.md"
    }
  ],
  "omittedPaths": [],
  "omittedTags": [],
  "updateOn": "file-open",
  "omitBookmarks": false
}